foliant/meta_commands/draw/__init__.py
foliant/meta_commands/draw/chapters_graph.py
foliant/meta_commands/draw/draw.py
foliantcontrib.project_graph-1.0.1.dist-info/LICENSE
foliantcontrib.project_graph-1.0.1.dist-info/METADATA
foliantcontrib.project_graph-1.0.1.dist-info/WHEEL
foliantcontrib.project_graph-1.0.1.dist-info/top_level.txt
foliantcontrib.project_graph-1.0.1.dist-info/RECORD
